{
  "users": [
    {
      "id": "ab12",
      "name": "joha",
      "email": "john@gmail.com",
      "phone": "9876543210"
    },
    {
      "id": "bc23",
      "name": "uday",
      "email": "uday@gmail.com",
      "phone": "7418529634"
    },
    {
      "id": "75a5",
      "name": "prathyusha",
      "email": "prathyusha@gmail.com",
      "phone": "7410258963"
    },
    {
      "id": "cb5d",
      "name": "sathwik",
      "email": "sathwik@gmail.com",
      "phone": "1234567890"
    }
  ],
  "products": [
    {
      "id": "p102",
      "name": "Smartphone",
      "price": 800,
      "ram": "16gb",
      "storage": "512gb",
      "color": "black",
      "phone": "iphone"
    },
    {
      "id": "p103",
      "name": "Laptop",
      "price": 2500,
      "ram": "16gb",
      "storage": "512gb",
      "color": "black"
    }
  ]
}